{
    "version": "1.0.0",
    "name": "Asgore",
    "assetPath": "characters/asgore",
    "singTime": 4,
    "isPixel": false,
    "scale": 1,
    "healthIcon": {
        "id": "asgore",
        "isPixel": false,
        "flipX": false,
        "scale": 1
    },
    "animations": [
        {
            "name": "idle",
            "prefix": "asidle",
            "offsets": [
                0,
                0
            ],
            "frameRate": 12,
            "frameIndices": []
        },
        {
            "name": "singLEFT",
            "prefix": "asleft",
            "offsets": [
                0,
                0
            ],
            "frameRate": 12,
            "frameIndices": []
        },
        {
            "name": "singDOWN",
            "prefix": "asdown",
            "offsets": [
                0,
                0
            ],
            "frameRate": 12,
            "frameIndices": []
        },
        {
            "name": "singUP",
            "prefix": "asup",
            "offsets": [
                0,
                0
            ],
            "frameRate": 12,
            "frameIndices": []
        },
        {
            "name": "singRIGHT",
            "prefix": "asright",
            "offsets": [
                0,
                0
            ],
            "frameRate": 12,
            "frameIndices": []
        }
    ],
    "flipX": false
}